rinoh_typeface_notosanscjk/README-Noto-Sans-CJK-JP.txt
rinoh_typeface_notosanscjk/SIL-OPEN-FONT-LICENSE.txt
rinoh_typeface_notosanscjk/__init__.py
rinoh_typeface_notosanscjk/notosanscjkjp-bold.otf
rinoh_typeface_notosanscjk/notosanscjkjp-regular.otf
rinoh_typeface_notosanscjk-0.0.1.dist-info/METADATA
rinoh_typeface_notosanscjk-0.0.1.dist-info/RECORD
rinoh_typeface_notosanscjk-0.0.1.dist-info/WHEEL
rinoh_typeface_notosanscjk-0.0.1.dist-info/entry_points.txt
rinoh_typeface_notosanscjk-0.0.1.dist-info/top_level.txt
