Metadata-Version: 2.1
Name: rinoh-typeface-notosanscjk
Version: 0.0.1
Summary: Noto Sans CJK typeface
Home-page: https://github.com/kumanoko24/rinoh-typeface-notosanscjk
Author: kumanoko
Author-email: noeleon930.hater.1@gmail.com
License: SIL Open Font License (OFL)
Keywords: opentype font noto sans notosans rinohtype rino rinoh sphinx
Platform: UNKNOWN
Classifier: Intended Audience :: Developers
Classifier: Intended Audience :: End Users/Desktop
Classifier: Operating System :: OS Independent
Classifier: Programming Language :: Python
Classifier: Programming Language :: Python :: 3
Classifier: Topic :: Text Processing :: Fonts
Requires-Dist: rinohtype
